{"path":"Roses","deepCounters":{"total":14,"images":14,"files":14},"counters":{"total":14,"images":14,"files":14},"thumb":{"path":"thumbs\/DSC02652.JPG","width":480,"height":360},"album":{"description":"Switzerland, Swiss Confederation. Spring 2022.\n\nBotanical, Zürich, Rhine, Falls, Switzerland, Swiss, Island, Flora, Mountains, River, Alps, City.","title":"Swiss 2022: Boris Melikian Expeditions Collection."},"objects":[{"path":"DSC02652.JPG","image":{"path":"slides\/DSC02652.JPG","width":2000,"height":1500},"thumb":{"path":"thumbs\/DSC02652.JPG","width":480,"height":360},"fileSize":13378736,"name":"DSC02652.JPG","comment":"                               ","fileDate":"2022-05-20T15:54:50.0Z","category":"image","camera":{"aperture":8.0,"exposureTime":"1\/250s","originalDate":"2022-05-20T15:54:50.0Z","cameraModel":"DSC-HX99","location":{"latitude":"47° 13' 35.42\"","lat":47.226505,"long":8.813187,"longitude":"8° 48' 47.47\""},"focalLength35mm":"35mm","resolution":"4896 x 3672","cameraMake":"SONY","isoEquivalent":200,"flash":"Flash did not fire","focalLength":"6mm"}},{"path":"DSC02653.JPG","image":{"path":"slides\/DSC02653.JPG","width":2000,"height":1500},"thumb":{"path":"thumbs\/DSC02653.JPG","width":480,"height":360},"fileSize":12591157,"name":"DSC02653.JPG","comment":"                               ","fileDate":"2022-05-20T15:55:00.0Z","category":"image","camera":{"aperture":8.0,"exposureTime":"1\/250s","originalDate":"2022-05-20T15:55:00.0Z","cameraModel":"DSC-HX99","location":{"latitude":"47° 13' 35.42\"","lat":47.226505,"long":8.813187,"longitude":"8° 48' 47.47\""},"focalLength35mm":"44mm","resolution":"4896 x 3672","cameraMake":"SONY","isoEquivalent":200,"flash":"Flash did not fire","focalLength":"7mm"}},{"path":"DSC02665.JPG","image":{"path":"slides\/DSC02665.JPG","width":2000,"height":1500},"thumb":{"path":"thumbs\/DSC02665.JPG","width":480,"height":360},"fileSize":11081426,"name":"DSC02665.JPG","comment":"                               ","fileDate":"2022-05-20T15:58:20.0Z","category":"image","camera":{"aperture":8.0,"exposureTime":"1\/640s","originalDate":"2022-05-20T15:58:20.0Z","cameraModel":"DSC-HX99","location":{"latitude":"47° 13' 35.51\"","lat":47.226532,"long":8.813096,"longitude":"8° 48' 47.15\""},"focalLength35mm":"60mm","resolution":"4896 x 3672","cameraMake":"SONY","isoEquivalent":200,"flash":"Flash did not fire","focalLength":"10mm"}},{"path":"DSC02666.JPG","image":{"path":"slides\/DSC02666.JPG","width":2000,"height":1500},"thumb":{"path":"thumbs\/DSC02666.JPG","width":480,"height":360},"fileSize":11081778,"name":"DSC02666.JPG","comment":"                               ","fileDate":"2022-05-20T15:58:20.0Z","category":"image","camera":{"aperture":8.0,"exposureTime":"1\/640s","originalDate":"2022-05-20T15:58:20.0Z","cameraModel":"DSC-HX99","location":{"latitude":"47° 13' 35.51\"","lat":47.226532,"long":8.813096,"longitude":"8° 48' 47.15\""},"focalLength35mm":"60mm","resolution":"4896 x 3672","cameraMake":"SONY","isoEquivalent":200,"flash":"Flash did not fire","focalLength":"10mm"}},{"path":"DSC02667.JPG","image":{"path":"slides\/DSC02667.JPG","width":1500,"height":2000},"thumb":{"path":"thumbs\/DSC02667.JPG","width":270,"height":360},"fileSize":13016430,"name":"DSC02667.JPG","comment":"                               ","fileDate":"2022-05-20T15:58:44.0Z","category":"image","camera":{"aperture":8.0,"exposureTime":"1\/500s","originalDate":"2022-05-20T15:58:45.0Z","cameraModel":"DSC-HX99","location":{"latitude":"47° 13' 36\"","lat":47.226665,"long":8.813064,"longitude":"8° 48' 47.03\""},"focalLength35mm":"62mm","resolution":"4896 x 3672","cameraMake":"SONY","isoEquivalent":200,"flash":"Flash did not fire","focalLength":"10mm"}},{"path":"DSC02668.JPG","image":{"path":"slides\/DSC02668.JPG","width":2000,"height":1500},"thumb":{"path":"thumbs\/DSC02668.JPG","width":480,"height":360},"fileSize":11721609,"name":"DSC02668.JPG","comment":"                               ","fileDate":"2022-05-20T15:59:02.0Z","category":"image","camera":{"aperture":8.0,"exposureTime":"1\/1000s","originalDate":"2022-05-20T15:59:03.0Z","cameraModel":"DSC-HX99","location":{"latitude":"47° 13' 35.97\"","lat":47.226658,"long":8.813057,"longitude":"8° 48' 47\""},"focalLength35mm":"122mm","resolution":"4896 x 3672","cameraMake":"SONY","isoEquivalent":200,"flash":"Flash did not fire","focalLength":"19mm"}},{"path":"DSC02669.JPG","image":{"path":"slides\/DSC02669.JPG","width":2000,"height":1500},"thumb":{"path":"thumbs\/DSC02669.JPG","width":480,"height":360},"fileSize":12009371,"name":"DSC02669.JPG","comment":"                               ","fileDate":"2022-05-20T15:59:06.0Z","category":"image","camera":{"aperture":8.0,"exposureTime":"1\/1000s","originalDate":"2022-05-20T15:59:06.0Z","cameraModel":"DSC-HX99","location":{"latitude":"47° 13' 35.96\"","lat":47.226654,"long":8.813053,"longitude":"8° 48' 46.99\""},"focalLength35mm":"122mm","resolution":"4896 x 3672","cameraMake":"SONY","isoEquivalent":200,"flash":"Flash did not fire","focalLength":"19mm"}},{"path":"DSC02670.JPG","image":{"path":"slides\/DSC02670.JPG","width":2000,"height":1500},"thumb":{"path":"thumbs\/DSC02670.JPG","width":480,"height":360},"fileSize":11998647,"name":"DSC02670.JPG","comment":"                               ","fileDate":"2022-05-20T15:59:06.0Z","category":"image","camera":{"aperture":8.0,"exposureTime":"1\/1000s","originalDate":"2022-05-20T15:59:07.0Z","cameraModel":"DSC-HX99","location":{"latitude":"47° 13' 35.88\"","lat":47.22663,"long":8.813069,"longitude":"8° 48' 47.05\""},"focalLength35mm":"122mm","resolution":"4896 x 3672","cameraMake":"SONY","isoEquivalent":200,"flash":"Flash did not fire","focalLength":"19mm"}},{"path":"DSC02683.JPG","image":{"path":"slides\/DSC02683.JPG","width":2000,"height":1500},"thumb":{"path":"thumbs\/DSC02683.JPG","width":480,"height":360},"fileSize":16610519,"name":"DSC02683.JPG","comment":"                               ","fileDate":"2022-05-20T16:04:28.0Z","category":"image","camera":{"aperture":8.0,"exposureTime":"1\/320s","originalDate":"2022-05-20T16:04:28.0Z","cameraModel":"DSC-HX99","location":{"latitude":"47° 13' 35.76\"","lat":47.2266,"long":8.813101,"longitude":"8° 48' 47.16\""},"focalLength35mm":"40mm","resolution":"4896 x 3672","cameraMake":"SONY","isoEquivalent":200,"flash":"Flash did not fire","focalLength":"7mm"}},{"path":"DSC02684.JPG","image":{"path":"slides\/DSC02684.JPG","width":2000,"height":1500},"thumb":{"path":"thumbs\/DSC02684.JPG","width":480,"height":360},"fileSize":11929245,"name":"DSC02684.JPG","comment":"                               ","fileDate":"2022-05-20T16:04:44.0Z","category":"image","camera":{"aperture":8.0,"exposureTime":"1\/640s","originalDate":"2022-05-20T16:04:44.0Z","cameraModel":"DSC-HX99","location":{"latitude":"47° 13' 35.85\"","lat":47.226624,"long":8.813136,"longitude":"8° 48' 47.29\""},"focalLength35mm":"83mm","resolution":"4896 x 3672","cameraMake":"SONY","isoEquivalent":200,"flash":"Flash did not fire","focalLength":"13mm"}},{"path":"DSC02685.JPG","image":{"path":"slides\/DSC02685.JPG","width":2000,"height":1500},"thumb":{"path":"thumbs\/DSC02685.JPG","width":480,"height":360},"fileSize":11941954,"name":"DSC02685.JPG","comment":"                               ","fileDate":"2022-05-20T16:04:44.0Z","category":"image","camera":{"aperture":8.0,"exposureTime":"1\/640s","originalDate":"2022-05-20T16:04:45.0Z","cameraModel":"DSC-HX99","location":{"latitude":"47° 13' 35.85\"","lat":47.226624,"long":8.813136,"longitude":"8° 48' 47.29\""},"focalLength35mm":"83mm","resolution":"4896 x 3672","cameraMake":"SONY","isoEquivalent":200,"flash":"Flash did not fire","focalLength":"13mm"}},{"path":"DSC02686.JPG","image":{"path":"slides\/DSC02686.JPG","width":2000,"height":1500},"thumb":{"path":"thumbs\/DSC02686.JPG","width":480,"height":360},"fileSize":14363586,"name":"DSC02686.JPG","comment":"                               ","fileDate":"2022-05-20T16:05:24.0Z","category":"image","camera":{"aperture":8.0,"exposureTime":"1\/400s","originalDate":"2022-05-20T16:05:25.0Z","cameraModel":"DSC-HX99","location":{"latitude":"47° 13' 35.94\"","lat":47.22665,"long":8.813001,"longitude":"8° 48' 46.8\""},"focalLength35mm":"24mm","resolution":"4896 x 3672","cameraMake":"SONY","isoEquivalent":200,"flash":"Flash did not fire","focalLength":"4mm"}},{"path":"DSC02687.JPG","image":{"path":"slides\/DSC02687.JPG","width":2000,"height":1500},"thumb":{"path":"thumbs\/DSC02687.JPG","width":480,"height":360},"fileSize":13365722,"name":"DSC02687.JPG","comment":"                               ","fileDate":"2022-05-20T16:05:30.0Z","category":"image","camera":{"aperture":8.0,"exposureTime":"1\/400s","originalDate":"2022-05-20T16:05:31.0Z","cameraModel":"DSC-HX99","location":{"latitude":"47° 13' 35.79\"","lat":47.22661,"long":8.813009,"longitude":"8° 48' 46.83\""},"focalLength35mm":"58mm","resolution":"4896 x 3672","cameraMake":"SONY","isoEquivalent":200,"flash":"Flash did not fire","focalLength":"9mm"}},{"path":"DSC02688.JPG","image":{"path":"slides\/DSC02688.JPG","width":2000,"height":1500},"thumb":{"path":"thumbs\/DSC02688.JPG","width":480,"height":360},"fileSize":13362176,"name":"DSC02688.JPG","comment":"                               ","fileDate":"2022-05-20T16:05:32.0Z","category":"image","camera":{"aperture":8.0,"exposureTime":"1\/400s","originalDate":"2022-05-20T16:05:33.0Z","cameraModel":"DSC-HX99","location":{"latitude":"47° 13' 35.79\"","lat":47.22661,"long":8.813008,"longitude":"8° 48' 46.83\""},"focalLength35mm":"58mm","resolution":"4896 x 3672","cameraMake":"SONY","isoEquivalent":200,"flash":"Flash did not fire","focalLength":"9mm"}}],"name":"Roses","theme":{"path":"pl-theme.jpg","width":2500,"height":1250},"fileDate":"2022-05-24T23:44:52.41Z"}